mazga_db/__init__.py
MazgaDB-1.1.2.dist-info/METADATA
MazgaDB-1.1.2.dist-info/WHEEL
MazgaDB-1.1.2.dist-info/top_level.txt
MazgaDB-1.1.2.dist-info/RECORD
