Metadata-Version: 2.1
Name: MazgaDB
Version: 1.1.2
Summary: ОРМ для базы данных SQlite
Home-page: https://github.com/Mazgagzam/MazgaDB
Author: Mazga
Author-email: agzamikail@gmail.com
License: UNKNOWN
Project-URL: Documentation, https://github.com/Mazgagzam/MazgaDB
Keywords: example python orm sql
Platform: UNKNOWN
Classifier: Programming Language :: Python :: 3
Classifier: License :: OSI Approved :: MIT License
Requires-Python: >=3.8
Requires-Dist: prettytable
